codeaudit/__about__.py
codeaudit/__init__.py
codeaudit/altairplots.py
codeaudit/api_interfaces.py
codeaudit/api_reporting.py
codeaudit/checkmodules.py
codeaudit/codeaudit.py
codeaudit/complexitycheck.py
codeaudit/filehelpfunctions.py
codeaudit/htmlhelpfunctions.py
codeaudit/issuevalidations.py
codeaudit/privacy_lint.py
codeaudit/pypi_package_scan.py
codeaudit/reporting.py
codeaudit/security_checks.py
codeaudit/simple.css
codeaudit/totals.py
codeaudit/data/sastchecks.csv
codeaudit/data/secretslist.txt
codeaudit-1.5.0.dist-info/METADATA
codeaudit-1.5.0.dist-info/WHEEL
codeaudit-1.5.0.dist-info/entry_points.txt
codeaudit-1.5.0.dist-info/licenses/LICENSE.txt
codeaudit-1.5.0.dist-info/RECORD
