Metadata-Version: 2.4
Name: codeaudit
Version: 1.5.0
Summary: Simplified static security checks for Python 
Project-URL: Documentation, https://github.com/nocomplexity/codeaudit#readme
Project-URL: Issues, https://github.com/nocomplexity/codeaudit/issues
Project-URL: Source, https://github.com/nocomplexity/codeaudit
Author-email: Maikel Mardjan <mike@bm-support.org>
License-Expression: GPL-3.0-or-later
License-File: LICENSE.txt
Keywords: Complexity Checker,Python SAST,SAST,SAST API
Classifier: Development Status :: 4 - Beta
Classifier: Environment :: Console
Classifier: Intended Audience :: Developers
Classifier: Intended Audience :: Science/Research
Classifier: Programming Language :: Python
Classifier: Programming Language :: Python :: 3.11
Classifier: Programming Language :: Python :: 3.12
Classifier: Programming Language :: Python :: 3.13
Classifier: Programming Language :: Python :: 3.14
Classifier: Topic :: Security
Classifier: Topic :: Software Development :: Quality Assurance
Requires-Python: >=3.8
Requires-Dist: altair>=5.5
Requires-Dist: fire>=0.7.0
Requires-Dist: pandas>=2.3
